README.md
setup.cfg
setup.py
nyroglancer/__init__.py
nyroglancer/extension.py
nyroglancer/hdf5_viewer.py
nyroglancer/intrusion.py
nyroglancer/ndstore.py
nyroglancer/shaders.py
nyroglancer/viewer.py
nyroglancer.egg-info/PKG-INFO
nyroglancer.egg-info/SOURCES.txt
nyroglancer.egg-info/dependency_links.txt
nyroglancer.egg-info/requires.txt
nyroglancer.egg-info/top_level.txt
nyroglancer/static/__init__.py
nyroglancer/static/chunk_worker.bundle.js
nyroglancer/static/index.html
nyroglancer/static/main.bundle.js
nyroglancer/static/styles.css