Metadata-Version: 1.0
Name: nyroglancer
Version: 1.0.3
Summary: jupyter extension for neuroglancer
Home-page: https://github.com/funkey/nyroglancer
Author: Jan Funke
Author-email: jfunke@iri.upc.edu
License: Apache License 2.0
Platform: UNKNOWN
